{
    "chapter_title": "第三十八章 ",
    "chapter_summary": "县委书记夏雨浓针对一些敏感问题发表了讲话，引起了县长于化奇、县委副书记文书苹等官员的关注。夏雨浓的讲话迅速成为了县城的头版新闻，引发了公众的热议。人们对此有不同的看法，有的人支持他的观点，认为他敢于直言；而有的人则为他担忧，担心这会对他的仕途产生负面影响。",
    "para_groups_num": 1,
    "para_groups": [
        {
            "id": 0,
            "content": "同时在台上的还有县长于化奇、县委副书记文书苹、县委组织部长邰任玉、政法委书记崔秉枢、县纪委书记郑宇清。\n他们都眼怔怔地看着夏雨浓，脸上带着一股子迷惘与茫然。\n而县长于化奇与副书记文书苹的脸色更是难看。\n夏雨浓的讲话第二天就传遍了全县，成为县城的头条新闻，人们在茶余饭后谈论时，第一句话就是，这个夏书记看样子要动真的了。\n但也有人替他担心，担心他招祸。",
            "summary": "县委书记夏雨浓针对一些问题发表讲话，引起了县长于化奇和县委副书记文书苹等人的关注。夏雨浓的讲话很快成为县城的头条新闻，人们议论纷纷，有的支持他，有的为他担忧。"
        }
    ]
}