{
    "chapter_title": "第二十四章 ",
    "chapter_summary": "金小龙与王雁曾是一对恋人，但在王雁找到新恋情后，两人的关系变得紧张。金小龙选择和平分手，尽管他仍然深爱着王雁。为了摆脱过去，金小龙购买了一套新房子，但却因此失去了拍摄电影的机会，导致他的艺术生命逐渐消逝。",
    "para_groups_num": 1,
    "para_groups": [
        {
            "id": 0,
            "content": "金小龙在绝望中也曾不屈不挠地努力过，他离不开王雁，他想让时间使王雁回心转意。他认为男女之间一时图个新鲜，过了这个劲也就过去了。在这期间，他不再过问王雁的行动，王雁什么时候回家，什么时候离开家，他从不多说一句话，只是用一种怨艾的目光望着王雁。王雁却不迎合他的目光，穿衣、化妆，然后义无反顾地走出去。\n王雁头也不回地走下楼，走到街边搭上车，金小龙站在窗前，一直看到王雁乘坐的出租车消失在茫茫的车流中，金小龙的心都碎了。\n那一阵，金小龙的心情灰暗到了极点，他自己都说不清那些日子是怎么过来的。明明知道自己心爱的女人出去和别的男人约会了，女人回家的时候，身上还带着那男人的气味，金小龙的心境便可想而知了。\n一天，王雁回到家里，金小龙那凄楚无助的目光又迎了过去。这回王雁的目光和他正视在了一起，王雁：你离还是不离？王雁的话，说得干脆而又利索。\n金小龙就满含希望地说：雁，想想以前咱们相爱的日子吧，难道你就真的不给我机会了吗？回来吧，我还会像以前那样爱你。\n寻找到新鲜爱情的王雁，觉得金小龙的话太可笑了。\n对于一个女人的身体和心都离开了的男人，还有什么好说的呢。王雁开始收拾自己的东西，金小龙睁着一一双迷离的眼睛望着，最后终于醒了过来，很干脆地跪在王雁面前，声泪俱下地说：雁，我求你了，我真的求你了。\n王雁决心已下，就是十头牛也拉不回了。如果这时金小龙冲上来，狠狠地抽她几个耳光，也许她还会有话对他说，而面对金小龙这种举止和行为，她真的一句话也不想说了。王雁收拾完自己的东西，头也不回地走了。\n金小龙就那么天长地久地跪在那里。他知道，王雁与那个男人公开同居去了。他欲哭无泪，欲喊无声。\n金小龙和王雁都是圈里人，发生了这样的事，大家很快就都知道了。在这之前，王雁和哪个男人眉来眼去，偷偷摸摸地有一腿，大家也都会睁只眼闭只眼，不好说什么。人嘛，尤其是圈里人，男男女女的有点什么事，大家都心照不宣，过去也就过去了。现在的形势发生了深刻的变化，他们的态度便从地下转移到地上，有人登门来安慰金小龙，有的打个电话探问虚实。人们都说：既然这样了，就离吧。\n金小龙不说话，把头仰靠在沙发上，绝望地望着天花板。\n人们又说：不离也没什么意思了，天涯何处无芳草呢。\n人们小心地选择着安慰金小龙的字眼，恐怕伤了他。\n金小龙不说离，也不说不离，就那么痴呆地绝望着。\n后来还是王雁打破了这种尴尬的局面。她在一天清晨给金小龙打来一个电话，这是她离家出走后第一次给金小龙打电话。她在电话里很平静地说：你看咱们足和平解决，还是用别的方式。\n金小龙当然明白王雁这句话的含意，和平解决就是协议离婚，别的方式自然是通过法院判决。\n王雁又说：和平解决对你我都有好处。你看着办吧。\n说完便放下了电话。\n王雁打过电话这天，是她离家出走一个月零十天。\n在这期间，金小龙在台历上做出了醒目的记号，日历每翻过去一页，金小龙都在上面画一个流血的心，红笔画的，很醒目。一个月又十天，金小龙度日如年。他曾一次又一次地幻想，王雁在某天清晨或者黄昏出现在他的面前，扑在他的怀里，一边哭一边请求他原谅，那该是怎样的感人场面呀。\n金小龙还是无可奈何地选择了用和平的方式解决了他们的问题，他太爱王雁了，爱得毫无道理，也毫无逻辑，他只能无条件地服从王雁，包括分手的方式和时间。\n金小龙在分手前向王雁提出了最后一个小小要求，他约她坐一坐。她答应了。那天傍晚，他们一起来到了“缘分酒吧”。这是他们以前非常喜欢的酒吧，不仅是名字，还有这里的氛围。他们曾在这里缠绵地述说爱情，这回却要在这里分离了。\n他们面对面坐着，两杯冒着热气的咖啡，一支摇曳的蜡烛。\n他还在说：雁，我真的爱你，没有你我不知怎么生活。\n他的双眼里布满了血丝。\n她不看他，望着眼前飘忽不定的蜡烛，幽幽地说：你真的爱我？\n他用劲地点点头才说：我可以发誓。说完就要去咬自己的中指，以前他向她表白爱情的时候，曾咬破过中指，当时感动得王雁泪水盈盈，她把他流血的中指含在嘴里，那么柔情蜜意地吸吮着。\n这次她却说：你不要这样，如果你真的爱我，就让我离开你。我现在真的很幸福，难道你不希望我幸福吗？\n他望着她，她的脸孔红润而又光鲜，他们相爱时，她也曾这么红润光鲜过。他绝望地闭上了眼睛，半晌才哽着声音说：我爱你，什么时候回到我身边我都欢迎。\n她无言。\n他又说：你以后注意身体，拍戏的时候要多睡眠。\n她抬起手腕看了一次表。\n他望着她，她的目光在他面前游移着。\n他再说：以后有什么事就给我打电话，我是你最好的朋友。\n他说这话时，泪水已在眼眶里打转了。\n她低头不语，望着那盏飘忽的蜡烛。\n他又说：他对你真的好？\n她又看了看表，然后点点头。\n他就不说什么了，似乎想不起该说什么了。\n沉默了半晌，她才说：那我就走了，回去太晚了，他不放心。\n他的心疼了一下。\n他把她送出酒吧，一直看着她坐的出租车驶出他的视野。\n和王雁分手后，金小龙很快买了这套房子。\n以前的房子空在那里，那里的一切依旧，他无法面对往昔的一切。\n他也无法拍戏，他的艺术生命也随着失败的爱情一起毁掉了。",
            "summary": "金小龙深爱着王雁，但王雁找到了新的爱情。在金小龙得知王雁和别的男人交往后，他们的关系变得紧张。金小龙选择了和平分手，尽管他深爱着王雁。在分手后，金小龙买了一套新房子，试图摆脱过去的回忆。然而，他无法拍戏，艺术生命也随之消失。"
        }
    ]
}