{
    "chapter_title": "第三十二章  尾声",
    "chapter_summary": "莫言松带领警察来到霍彤家中调查一起神秘失踪案。然而，他们发现霍彤的尸体不见了，现场只剩下一颗被取走的心脏。与此同时，周楚楚正在密室里忙碌地缝合一具面目狰狞的尸体。面对莫言松的询问，她毫无反应，全神贯注地完成缝合工作后，露出了幸福的微笑。这个章节充满了悬疑和惊悚，揭示了隐藏在案件背后的惊人秘密。",
    "para_groups_num": 1,
    "para_groups": [
        {
            "id": 0,
            "content": "莫言松带着警察冲进霍彤家的时候，却发现一层没有人，他立刻跑向了二层，当他冲进密室的时候，看到眼前的情景，却不禁愣住了。\n密室很冷，像一个冰库，而里面的地上躺着霍彤的尸体，他的左胸前有个血洞，里面是空的心脏不见了。\n而周楚楚却坐在冰床上缝着一具狰狞恐怖的尸体……\n“楚楚，你在干什么？”\n莫言松不敢相信自己的眼睛。\n周楚楚却似乎根本没有听到莫言松的声音，只是坐在冰床上静静地缝着，认真地缝着，根本没有在意是否有人来，她的目光全部集中在那具尸体上，当最后一针终于缝好的时候，她的脸上露出了幸福的微笑……",
            "summary": "莫言松带警察闯入霍彤家，发现家中无人且霍彤尸体失踪，心脏被取走。周楚楚在密室冰床上缝合一具狰狞恐怖的尸体，对莫言松的询问置若罔闻，专注地完成缝合后露出幸福微笑。"
        }
    ]
}