{
    "novel_title": "风水奇谭4：昆仑灵谷",
    "tag": "['武侠', '奇幻', '惊悚']",
    "source": [
        0,
        1,
        2,
        3,
        4,
        5,
        6,
        7
    ],
    "content": "第1部分：在金万流与灰衣人的对决中，金万流虽占优势，但无法击败灰衣人。双方在激烈较量中，灰衣人凭借对开山掌的了解和敏捷化解金万流的攻击。金万流试图利用先机和十三势开山掌击败灰衣人，但仍无法实现。在风冷情的帮助下，金万流逃脱并反击，成功击断灰衣人的长剑。然而，风冷情仍避免与灰衣人直接对抗，以保持自己的身份和水灵的隐秘。灰衣人认出风冷情的身份，威胁要找他报仇。风冷情决定光明正大地帮助金万流对抗灰衣人。灰衣人挥舞碎梦刀，威力大增，金万流不得不躲避。灰衣人突然出现又离去，令人感到意外。\n第2部分：风冷情、云高崖和铁中坚等人面临一系列挑战，包括神秘的黑衣女子、摸金派弟子、武林高手以及传说中的血尸。他们在寻找失踪师侄、师傅和宝物的过程中，揭示了一个关于龙脉、龙眼和守护者的神秘世界。在这场冒险中，他们不仅战胜了强大的敌人，还收获了珍贵的友谊和成长。\n第3部分：摸金派三代弟子分成两组，一组在昆仑山口欣赏美景，另一组深入昆仑山探险。他们在寻找线索时遇到奇怪脚印和神秘的骆驼峰、棺材峰等地，还在地狱谷中发现脚印并未引发天雷。在遭遇伏击后，他们爬上峰顶，发现一个形似棺材的大石，里面有一个幽深的山洞。在深入山窟过程中，他们遇到黑翼蝙蝠等危险，但在饕餮的带领下，他们继续前行，寻找师尊金万流。\n第4部分：师傅和卸岭寨副寨主为寻找千年雪莲救治患病三师叔，闯入昆仑山，遭遇神秘三眼太岁。副寨主被咬伤，师傅利用僵尸粉将其困住。他们发现雪莲与三眼太岁共生，难以采摘。师傅开始寻找罪魁祸首灰衣人。众人发现复活的三眼太岁，引发恐慌。铁中坚因未带僵尸粉而烦恼，众人四处逃窜。风冷情试图阻止三眼太岁，但未能成功。饕餮为保护风冷情，与三眼太岁展开激战，却被其吞入腹中。风冷情沿暗河逃跑，三眼太岁紧追不舍。一群尸蟾出现，与三眼太岁对抗，使其逐渐萎缩失去战斗力。众人继续寻找灰衣人。\n第5部分：一群人在寻找传说中的王陵和朱果时，意外发现了西王母陵墓和小宛国主的守护。他们在陵墓中遇到了神秘少年虚影和冰层下的胡服臣民，揭示了西王母在大灾难后的消失以及龙卷风的神秘能力可能与他突厥王朝后裔的身份有关。\n第6部分：云高崖和熊猫在一座古墓中发现疑似汗血宝马的尸骸和和田玉器皿，却在主墓室内找到一口绿玉棺。云高崖试图复活棺内两具尸骸，引发同伴们的惊讶和恐惧。风冷情推测云高崖中的毒可能与二层冰面上的人形黑影有关。为了找出毒物并寻找解药，众人开始寻找线索。熊猫面临寻找失踪外公、揭开师兄弟们死亡真相以及解决云四叔生死问题的困境。同时，风冷情和铁中坚研究一种名为番木鳖的神秘毒素。熊猫等四人遇到番木鳖，讨论治疗方案时引发绿玉棺内的小宛国主尸变。众人躲避小宛国主的攻击，成功解救云高崖。\n第7部分：一群武林高手为了解救被囚禁的外公，深入一座神秘的阴阳墓寻找尸丹和阴丹。他们在墓中发现了一段丰富的历史，包括大宛国主和小宛国主的陵墓，以及西王母的陵寝。在这个过程中，他们不仅要面对墓中的危险，还要揭开玉棺中男子的身份之谜，以及处理彼此之间的情感纠葛。他们在克服重重困难后，成功解救了外公，并揭示了这个古墓背后的秘密。\n第8部分：一段关于冒险和友谊的故事，讲述了一群人在寻找传说中的肉仙芝母过程中，逐渐建立深厚的友谊。在这个过程中，他们面临着各种困难和挑战，如灰衣人的追杀、身世的揭示等。这些困难使他们更加团结，也让他们在面对生死抉择时展现了勇敢和智慧。他们找到了肉仙芝母，解决了风冷情的身世之谜，并在经历了一系列的冒险和挑战后，收获了成长和感悟。",
    "summary": "一群武林高手为了各自的使命和目标，展开了惊心动魄的冒险。金万流与灰衣人的对决成为故事的核心，双方在不同场合展开激战，却始终无法分出胜负。在这个过程中，风冷情、云高崖和铁中坚等人逐渐揭开了关于龙脉、龙眼和守护者的神秘世界。他们的冒险旅程充满了挑战和危险，包括神秘的黑衣女子、摸金派弟子、武林高手以及传说中的血尸。在这场冒险中，他们不仅战胜了强大的敌人，还收获了珍贵的友谊和成长。在这个过程中，他们不仅揭示了关于龙脉、龙眼和守护者的神秘世界，还收获了珍贵的友谊和成长。他们的冒险旅程充满了挑战和危险，包括神秘的黑衣女子、摸金派弟子、武林高手以及传说中的血尸。在这场冒险中，他们不仅战胜了强大的敌人，还收获了珍贵的友谊和成长。"
}