{
    "chapter_title": "第三百三十一章 无影无踪",
    "chapter_summary": "叶惊天怀疑卸岭寨的龙寨主和木寨主可能知道通往墓道的秘密机关。为了找到他们，叶惊天建议团队按原路返回并留意沿途的线索。在返回途中，队员们仔细检查了石壁和地面的足迹，但并未发现童人蛊的踪迹。",
    "para_groups_num": 1,
    "para_groups": [
        {
            "id": 0,
            "content": "叶惊天继续道：“那卸岭寨的龙寨主和木寨主一定知道这墓道里面的机关，这才趁着咱们不备之机，隐匿而去。咱们只要破解开这墓道的机关，便势必能够找到那龙寨主和木寨主二人的行踪。”顿了一顿，叶惊天又道：“这二人是要甩开咱们，独吞这墓道之中的冥器。”\n龙门鬼王咬牙切齿道：“不错，小兄弟说的甚是。这姓龙的和姓木的都是卑鄙小人，要是再被咱们抓到，一定要将这二人扔到那水龙卷里面。”顿了一顿，龙门鬼王似乎想起一事，皱眉道：“现在怎么办？这墓道里面的机关谁会破？”\n叶惊天微微一笑，道：“鬼王前辈，难道你忘了我们的身份了？”\n龙门鬼王抬眼看着叶惊天和历星魂，一拍自己的脑袋，道：“哎呦，我怎么忘了，你们二位是——”\n叶惊天摆摆手，示意龙门鬼王不要继续说下去。\n龙门鬼王随即缄口不说。\n那于老七却望着叶惊天和历星魂二人，若有所思。\n乐七星也是饶有兴味的看着叶惊天和历星魂，似乎对这二人大感兴趣。\n叶惊天并不在意二人的眼光，对龙门鬼王道：“这一次咱们按照原路返回，一路之上慢慢走，看看这两侧的石壁有些什么古怪。还有，沿路走的时候，再仔细查看一下地上的足迹。——那龙木两位卸岭寨的寨主终究不能平地消失。”\n龙门鬼王点点头，道：“小兄弟所说的甚是。”众人当即手持火折子向来路走了回去。\n一路之上，众人晃动火折子向两侧石壁照去，却见这两侧石壁除了有些潮湿之外，并无特异之处。走出百十丈外，只见地上脚印杂乱，看来这便是适才众人遇到那童人蛊的地方。抬眼向前望去，那童人蛊却不在前方。\n众人又是一怔。\n适才转了一圈，众人两次遇到那童人蛊，本以为众人所走的墓道乃是跟鬼打墙一般，循环往复。\n谁料想这一次却是没有看到那一只童人蛊。\n那童人蛊去了那里？\n众人心头都是掠过一道阴云。",
            "summary": "叶惊天认为卸岭寨的龙寨主和木寨主可能知道墓道内的机关，他们趁人不备时离开。叶惊天提议按原路返回寻找他们的踪迹。一路上，众人检查石壁和地面足迹，但没有找到童人蛊。"
        }
    ]
}