{
    "chapter_title": "第三百四十三章 骷髅头骨",
    "chapter_summary": "在龙门鬼王的提议下，叶惊天与鬼王共同探讨血池中是否藏有珍贵宝物。为了寻找答案，他们决定邀请卸岭寨副寨主、摸金校尉龙寨主前来探查血池。龙寨主展示了他独特的盗墓工具——探阴爪，这让叶惊天意识到摸金校尉和卸岭力士在这个领域的专长。",
    "para_groups_num": 1,
    "para_groups": [
        {
            "id": 0,
            "content": "龙门鬼王奇道：“小兄弟，怎么了？”\n叶惊天沉声道：“鬼王前辈，我看咱们还是让那龙寨主探查一下，这血池里面有没有价值连城的珍宝吧？”\n这一提醒，龙门鬼王立时明白过来，当即将手缩了回去，向龙寨主道：“这小兄弟说的甚是。龙寨主身为卸岭寨的副寨主，自是对于这古墓之中的各种机关了如指掌。还是龙寨主施展妙手，将这血池之中的珍宝取出来吧。”\n龙寨主肚里暗骂叶惊天多事，脸上却是露出笑容，道：“这个自然，鬼王前辈一旁稍侯，看晚辈来取出这血池之中的物事。”\n只见龙寨主从背后行囊之中伸手一掏，取出一根半尺来长的物事，伸手攥住那物事的两端，用力一拉，那物事立时便变成三尺来长。前端一个鹰爪般的物事，后面便是一个黑黝黝的铁棍。\n叶惊天目光闪动，缓缓道：“探阴爪？”\n龙寨主侧目向叶惊天望去，心中暗暗惊奇：“这小子懂得倒是真多。”\n当即向叶惊天咧嘴一笑道：“不错，这正是探阴爪。”\n这探阴爪乃是倒斗摸金一脉中，摸金校尉和卸岭力士才有的盗墓利器。\n只不过摸金校尉的乃是抓端有四根利爪，卸岭力士却只有三根利爪。两种探阴爪的功用基本相同。都是盗挖古墓之际，以这探阴爪于那棺木之中掏挖墓中的冥器所用。\n当下，龙寨主手持探阴爪，迈步走到血池之前。将那探阴爪伸了进去。\n龙寨主目注血池，手中探阴爪来回在池中梭巡。片刻之后，龙寨主眉头一皱，手中探阴爪停了下来。原来在这一瞬之间，龙寨主手中的探阴爪勾住血池池底的一件物事。\n龙寨主慢慢将那探阴爪向上提起，随着哗啦一声，那物事被龙寨主的探阴爪勾了出来。\n这一勾出来，众人举目望去，都是吓了一跳。\n原来龙寨主手中探阴爪所勾住的赫然是一棵骷髅头骨。\n龙寨主也是心中一凛，不由自主退后数步。\n那被探阴爪勾出来的骷颅头骨也随即被龙寨主勾出，落在地上。",
            "summary": "龙门鬼王和叶惊天讨论关于血池中是否有价值连城的珍宝。龙门鬼王建议请卸岭寨副寨主、摸金校尉龙寨主来探查血池。龙寨主拿出盗墓利器探阴爪，叶惊天认出这是摸金校尉和卸岭力士才有的盗墓利器。"
        }
    ]
}