{
    "chapter_title": "第三十七章 杀不得",
    "chapter_summary": "肥龙的手下肥虎试图杀死叶惊天，但在关键时刻，朱四娘突然出现并救下了叶惊天。肥虎惊讶于朱四娘的举动，她解释说不能杀叶惊天。这段摘要概括了章节中肥龙对叶惊天的敌意、叶惊天被迫逃亡的情景以及朱四娘的正义行为。",
    "para_groups_num": 2,
    "para_groups": [
        {
            "id": 0,
            "content": "这一句话从肥龙的口中冷冰冰的说出，南三全，女屠户，铁二娘，等人或是杀人不眨眼的魔王，或是手上有数十条人命，听了此话，都是若无其事，只有叶惊天情不自禁打了一个寒噤。\n恰于此时，那肥龙转过头来，眼睛在叶惊天脸上上上下下打量了一番，而后皱起眉头，冷冷道：：“这个小娃娃带着多有累赘。老二，去把他杀了。”\n叶惊天大吃一惊，转身便向那通道之中跑了进去。心中骂道：“你这个杀千刀的，拿老子也当那些卸岭力士了，是不是？”此时此刻，叶惊天只想赶快逃离这里，就算得不到那解药，三个月后中毒而死，也好过立时毙命。\n肥虎狞笑一声，道：“好。”迈步便向那叶惊天追了过去。\n只听得肥虎脚步声蹬蹬蹬蹬向那叶惊天直奔而去。\n叶惊天还只十岁，人小腿短，那里能跑得过这人高马大的肥虎？眼看立时便要被这肥虎追上。\n肥虎右手蹭的一声拔出匕首，脸上笑意更浓，挥刀便向那叶惊天后心刺去。\n铁二娘和彭大春心中都是暗自不满。这叶惊天本是他们设下陷坑，这才捉到，用以当做人质，好要挟那叶隐，谁料想在这竖井之中，那肥虎轻轻易易的便下令杀死这个少年。——你让这二人心中如何不怒？\n只不过铁二娘和彭大春身处梅山六怪之间，群敌环伺，心中虽怒，但也只能强自忍耐。只不过对于这肥龙所说的话更是无法相信——对于一个已经被他下了剧毒的小孩子，他都不肯放过，这肥龙所说的话，还有什么可以相信？\n叶惊天惊慌失措之际，脚下一个趔趄，跌倒在通道之中。",
            "summary": "肥龙将一名叫叶惊天的少年视为累赘，命令手下肥虎将他杀死。叶惊天惊慌失措地逃跑，但被肥虎追赶并持刀刺向后背。铁二娘和彭大春虽然对肥龙的决策感到不满，但他们身处困境，无法阻止。"
        },
        {
            "id": 1,
            "content": "那肥虎拔刀便上。\n便在这千钧一发之际，肥虎只觉身后有一件利器刺了过来。\n肥虎心中一震，急忙滚倒在地，向一旁闪了开来。而后迅捷飞身站起，向那身后偷袭自己之人望去，却见那人矮矮胖胖，手握一把杀猪刀，却是那女屠户朱四娘。\n肥虎愕然道：“四妹，你干什么？”\n女屠户皱皱眉，走到那叶惊天跟前，将叶惊天扶了起来，拍了拍他身上的灰尘，正色道：“这个孩子不能杀。”",
            "summary": "肥虎与叶惊天展开激战。就在关键时刻，肥虎突然感到背后受到袭击，原来是女屠户朱四娘手持杀猪刀偷袭。肥虎惊讶地问朱四娘为什么要这么做，朱四娘解释说她不能杀叶惊天。"
        }
    ]
}