{
    "chapter_title": "第五十九章 擒鼠先擒王",
    "chapter_summary": "叶惊天在女屠户的帮助下成功捕获了白毛老鼠，引发了周围大量灰鼠的敌意。然而，在女屠户的支持下，叶惊天勇敢地面对这些敌人，紧紧抓住老鼠不放松，成功度过危机。",
    "para_groups_num": 1,
    "para_groups": [
        {
            "id": 0,
            "content": "叶惊天一颗心怦怦直跳。心里暗暗道：“白毛老鼠啊白毛老鼠，你可千万别醒啊。”就在叶惊天一只手将要伸到那白毛老鼠的身上时，那只白毛老鼠募地醒了过来，发出吱的一声。\n叶惊天吓了一跳，一只右手便没有伸将下去。\n女屠户着急道：“快抓啊叶惊天。”\n叶惊天眼睛一闭，右手前伸，一把抓住那只白毛老鼠。使劲攥住。\n那只白毛老鼠又是发出吱吱数声。围在叶惊天身旁的群鼠一阵骚乱。\n叶惊天哆里哆嗦的睁开眼睛，向四周望去。只见数万只灰鼠的眼睛俱都望着自己。那一只只灰鼠的眼睛之中满是怨毒之意。\n叶惊天不禁吓了一大跳。\n女屠户和南三全眼见叶惊天将那只白毛老鼠捉入手中，大喜。\n数万只灰鼠果然如二人所料，投鼠忌器再也不敢稍动。女屠户招呼叶惊天道：“叶惊天，过来，记住千万别松手。”\n叶惊天只觉喉咙发干，于是又咽了一口唾沫，点了点头。一只右手死死攥着那只白毛老鼠，慢慢向女屠户走了过去。\n群鼠不由自主闪开一条通道。\n叶惊天看着数万只灰鼠眼睁睁望着自己，心中大是恐惧，不由自主加快脚步，走到女屠户身前。\n女屠户一把抱住叶惊天，叶惊天一颗心这才稍安。抬起头，向着女屠户道：“姑姑，我没哭。”口中虽是如此说，但是眼眶之中早已潮湿。\n适才被那鬼道人抛向那鼠群之时，叶惊天心里又恨又怕。待得女屠户坚决不舍自己，跟肥龙等人翻脸，执意要在这里相救自己。叶惊天那时候已经知道，日后只要这女屠户吩咐自己做任何事情，自己都是绝不推辞。纵使是赴汤蹈火，也是在所不辞。\n因为在这个少年心中始终坚信，别人对他一分好，他就要还别人千分万分。纵使是搭上自己的性命，也在所不惜。\n女屠户拍拍叶惊天的后背，低声道：“没事了，叶惊天，有姑姑在。\n不怕。”\n叶惊天点点头。\n一颗心渐渐凝定。\n那只白毛鼠王眼睛骨碌碌乱转，望着三人。",
            "summary": "叶惊天在女屠户的帮助下，成功地抓住了白毛老鼠。这一幕引起了周围数万只灰鼠的怨毒目光。尽管面对这么多敌人，叶惊天在女屠户的支持下，勇敢地走向她并紧紧握住老鼠不放。他们成功度过了这个危机。"
        }
    ]
}