{
    "chapter_title": "第九百零五章 冷血无情",
    "chapter_summary": "风啸天要求叶惊天证明他有保护他的能力，于是两人约定共度两个时辰。然而，风啸天并未告知具体的时间。在寻找神柜的过程中，叶惊天、历星魂和风慕容发现了空荡荡的巨棺，里面只有一些大东珠，并没有找到神柜。",
    "para_groups_num": 1,
    "para_groups": [
        {
            "id": 0,
            "content": "风啸天哈哈一笑，道：“这有何难解的？风某倘然不使出如此手段，怎么能够知道你有没有这一份实力，可以为风某守护这两个时辰？可以让风某平安无虞？那十八具铁僵尸挡你们不得，某家这才可以将一条性命交付于你。”\n叶惊天缓缓道：“那倘然我们二人就此丧命于那些铁僵尸手下呢？”\n风啸天嘿然一声，道：“那也是无法可想。某家只有另谋办法。”\n叶惊天冷哼了一声，没有说话。心中暗道：“这姓风的冷血无情，实难以常人心思度之。一俟此间事了，须得急速离开，免得被这贼子暗中下了毒手。只是这贼子如此奸猾，竟是丝毫不吐露那神柜的所在。”\n正沉吟之际，那风啸天皱起眉头，冷冷道：“叶惊天，你心中还有什么问题，一总问出来吧，免得这么婆婆妈妈。”\n叶惊天想了想，沉声道：“好，风先生，我们既然已经答应阁下，自是决不食言，待会自是为阁下守足两个时辰，在这两个时辰之内，我定当誓死周旋，不让其他人等伤到先生。这个风先生大可放心。”\n风啸天十分满意，点点头，道：“便是如此。”\n站在一侧的风慕容忽然开口道：“就是不知道风先生的这两个时辰是从几时到几时？”\n风啸天眉尖一挑，心中道：‘这个小姑娘倒是心细如发。”当下，目光望着叶惊天，缓缓道：“我只要你从亥时到丑时，这两个时辰保我平平安安，两个时辰之后，你便可带同其他两位自行离去。到那时，我是否灰飞烟灭，是否化为枯骨，一概与阁下无关。”\n叶惊天点点头，道：“好。”\n风啸天见叶惊天答应下来，便不再说话，一双目光从三人身上一一扫过，随即自行走到那巨棺之前，挨着那一具背靠巨棺的胡服男子的尸骸，坐了下来。随即闭上双目。双手搭在膝盖之上。竟似闭目凝思起来。\n叶惊天和风慕容对望一眼，二人心中都是转过一个念头：“那神柜究竟被这风啸天藏在何处？”\n叶惊天用目光示意历星魂和风慕容稍待，自己则慢慢走向那巨棺之前。\n风啸天始终紧闭双目，对于叶惊天的脚步声是充耳不闻。\n片刻之后，叶惊天来到那巨棺之侧，将身子凑到那巨棺之旁，举目向那巨棺之中望了过去。只见那巨棺之中空空荡荡，除了棺头有一只白玉枕之外，便是在巨棺的里面放置了数百颗大东珠。\n这些大东珠都是一般大小，圆润光泽，看来是放置在巨棺之中，防止尸骸□□之用。\n叶惊天眼睛在那巨棺之中转了一圈之后，还是未曾看到那神柜的踪影，不由得心里面微微失望。\n当下，叶惊天转过身来想，向着正自凝神望向自己的历星魂摇了摇头，意思没有寻到。\n历星魂也是心中颇为失望。\n叶惊天抬起头，环顾四周，只见这墓室东侧顶端，正中央的位置竟是有一个拳头大的孔洞。\n叶惊天迈步走到那东侧石壁之下，仰头上望，只见那孔洞黑漆漆的也不知道究竟有多深。\n叶惊天心中一动：“这拳头大的洞孔有何用处？”",
            "summary": "风啸天要求叶惊天和他一起度过两个时辰，以证明叶有守护他的能力。叶惊天答应下来，但风啸天并未透露这段时间的具体时间。叶惊天、历星魂和风慕容在寻找神柜的过程中，发现巨棺内空空荡荡，仅有一些大东珠，并未找到神柜。"
        }
    ]
}