{
    "chapter_title": "第一章 节：夜异（1）",
    "chapter_summary": "雅问在暴雨中回到了她久未回家的家。当她走进家门时，发现家里的环境并没有发生太大的变化，仿佛时间在这里停滞。她在书房里意外地发现了一具已故父亲的尸体，雷克满脸血迹，似乎是在看书时突然死亡的。罗婶表示当时房间里只有雷克一人，这让雅问感到非常疑惑。她开始寻找其他家人的踪迹，试图解开这个谜团。",
    "para_groups_num": 1,
    "para_groups": [
        {
            "id": 0,
            "content": "当雅问赶到家的时候，浑身都湿透了。外面的雨下得不是一般的大，她浑身上下不论在哪随便一拧都能拧出一大堆水来。\n她站在门口，抬头望着客厅上方的大吊灯，心头涌上了一阵久违的酸楚。\n一晃已经十六年没回来了，这里的一切竟然一点都没有变。\n一个人走过来接过了她手里的包。她扭头一看，是那个老佣人罗婶。\n“罗婶，爸爸是在书房吗？”她问。\n“是。”\n得到了回答后，她立刻三步并做两步冲上了二楼。一推开书房的门，她就见到了她已死去的父亲雷克。\n他随随便便地靠在椅子上，一只手悠闲地搁在书桌上，书桌上还摊开着一本书。可是他的眼睛里、鼻孔里、耳朵里、嘴角里都有暗红色的血迹。\n那些血迹都已经干涸发硬，在他脸上形成一条条粗直的血路，像一张狰狞的鬼脸。\n从傍晚时分她接到罗婶打来的电话知道爸爸死亡的消息之后，她就在回来的路上做好了各种各样的心理准备，可是她还是没有料到，爸爸的死状竟然会这么惨。\n看起来他像是在看书的时候猝不及防死亡的。\n“罗婶，这倒底是怎么回事？爸爸是怎么死的？”她的声音开始有了哭腔。\n“傍晚的时候，我正在厨房做饭，突然听到老爷在楼上‘啊’地大叫了一声，声音特别大，听起来怪吓人的”罗婶似乎还陷在当时的惊惧里，声音带着一丝慌乱，“我当时被吓坏了，心想一定出事了，立刻上楼去看，结果一推开书房的门，就发现老爷已经、已经死了，满脸都是血，就像现在这样。”\n“当时屋里还有别人吗？”\n“没有别人，就只有老爷一个人。”\n她忍不住用手摸了摸紧蹙的眉头：这还真是有点奇怪，怎么会没有人呢？\n“那家里其他人在什么地方？”\n她又问。",
            "summary": "雅问在暴雨中回到家，发现家里的一切都未改变。她在书房找到了已故的父亲雷克，他的尸体满脸血迹，看起来像是在看书时突然死亡。罗婶表示当时房间里只有雷克一人。雅问感到疑惑，家人在哪里？"
        }
    ]
}