{
    "chapter_title": "第八十章 节：你是谁（3）",
    "chapter_summary": "大哥和二哥意外地进入了神秘的冰窖，却失去了联系。妹妹在得知这个消息后，开始担忧二哥的安危。大哥向妹妹描述了冰窖中的诡异声音，但无法确定原因。妹妹怀疑这是上次试图伤害他们的人所为，但大哥并不认同。画面中出现了一个被绑在树上的人，让妹妹惊恐不已，怀疑她就是被\"第三只手\"抓走的小美。整个章节充满了紧张气氛，让人不禁为他们的命运捏一把冷汗。",
    "para_groups_num": 2,
    "para_groups": [
        {
            "id": 0,
            "content": "大哥僵僵地看着她，眼睛里带着一种深深的恐惧，突然伸手猛地抓住了她的胳膊，连指甲都嵌进了她的肉里，疼得她直咧嘴。\n大哥的手好冷，好冷。\n“老二他、他和小美一样，被第三只手抓走了！”大哥这样说的时候，眼角就开始不停地颤抖。\n“怎么回事？”她急忙追问到。\n“我也不知道，正走着走着，他就突然不见了！”\n大哥充满恐慌的声音立刻让她感到眼前一片恍惚：又是一起突然蒸发事件！\n“你不是一直和他呆在一块儿么！那你怎么会不知道？人怎么不见了？”她怔怔地问。\n“我们俩进去的时候，确实在呆在一起的，后来越往里走就听到冰窖里有声音，我和雷东都被那声音搅得胆战心惊的，渐渐地就拉开了距离。后来走着走着，我就发现他不见了，我一点察觉都没有，也不知道他是什么时候不见的，当时我光顾着听那声音了。”\n“到底是什么声音？”\n大哥想了想，又烦躁地摇了摇头：“我还是确定不了，那声音……听起来像是有人在说话，又好像是有人在哭，又好像是刮风的声音……反正，断断续续的，听着怪吓人的。”\n“那后来呢？”\n“后来，我发现老二不见了以后，就赶紧顺着原路回去找他，我一直喊他，后来就看到他掉在地上的手电筒，已经熄了火。”\n“会不会是上次要砸死我们那个人？会不会是他干的？”\n“可是我们刚才进去并没有发现冰窖里藏着人，上次那个人也好像彻底不见了。”\n怎么可能？她一皱眉。\n难道二哥真得和小美一样被“第三只手”抓走了？\n“怪不得妈妈不让咱们进这个冰窖！怪不得！”",
            "summary": "大哥和二哥进入一个神秘的冰窖，却在途中失去了联系。大哥惊恐地告诉妹妹，二哥也被\"第三只手\"抓走了。妹妹追问下，大哥描述了冰窖中听到的诡异声音，但无法确定具体原因。妹妹怀疑是上次试图砸死他们的人所为，但大哥认为冰窖内并未发现藏身之人。现在，妹妹开始担忧二哥真的像小美一样被\"第三只手\"抓走。"
        },
        {
            "id": 1,
            "content": "听着大哥的声音，她眼前突然浮现出了一副图画：黝黑的山岗、阴暗的天空、枯萎的树枝、干涸的土地，大风忽忽地刮，满地落叶，树上绑着一个披头散发的人，是小美……。\n“啊！”\n她忍不住惊叫了出来，用手按住自已的胸口，心脏咚咚咚跳得好快。",
            "summary": "黝黑的山岗、阴暗的天空、枯萎的树枝和干涸的土地。画面中有一个被绑在树上的披头散发的人，她认为是自己和小美。这个场景让她惊恐地尖叫出来，并用手捂住胸口，心跳加速。"
        }
    ]
}