{
    "novel_title": "布谷鸟的回声",
    "tag": "['武侠', '历史', '都市']",
    "source": [
        0,
        1
    ],
    "content": "第1部分：这部作品通过李世荣回乡的回忆，展现了农村生活的点滴和人们在困境中的抉择。故事中，黄狗蛋用一瓢水换来妻子芸香，但她的意外死亡使家庭生活陷入困境。李世荣帮助他们，并与程氏一起关注两个儿子根明和根亮的成长。根明勤奋诚实，而根亮顽劣，两人在成长过程中学会互相理解和支持。此外，作品中还涉及了家庭伦理、道德观念、友谊、责任和生活困境等主题，展现了生活中的喜怒哀乐和挑战，以及人们在面对困境时的勇气和智慧。\n第2部分：根亮在寻找靳红美的过程中结识了孙晓平，并将其交给公安机关。他在四川探望黎娟霞，并在煤矿认识了郭老头。他们在煤矿度过了一段欢乐时光，直到冬天，根亮去城里购买食物和酒。在回程途中，他遇到了一些奇怪的事情。回到矿区后，他和郭老头共同度过了接下来的日子。根亮离开后，来到清水县城寻找齐老头，希望能一起做生意，但未找到。他在那里遇到了唱灯影的黄武英和他的女友樱桃。根亮回到家乡，与哥哥根明团聚。他们谈论根亮的经历和他未带回来的钱。根明和根亮决定为根亮和女朋友安排见面。同时，他们得知怀文家发生变故，妻子秋桃回了娘家。根亮决定帮忙寄信并寻找失踪多年的父亲李世荣。在崆峒山上，根亮四处打听，领悟到父亲其实在他心中。尽管面临困难，但在家人支持下，根亮决定来年再找。年底时节，三太爷因根亮回家愤怒，准备在除夕夜教训他。同时，根明发现永贵的女人还活着，她在外地唱牛皮灯影。根明和根亮为她上坟，震惊于她的死讯。这个充满人情世故的故事展现了人性的复杂和矛盾，以及愤怒和悔恨之间的转变。",
    "summary": "这部作品通过李世荣回乡的回忆，讲述了农村生活中的人们在困境中的抉择和成长。故事围绕根明和根亮的成长展开，讲述了家庭伦理、道德观念、友谊、责任和生活困境等主题。根亮在寻找靳红美的过程中结识了孙晓平，并将其交给公安机关。他在四川探望黎娟霞，并在煤矿认识了郭老头。他们在煤矿度过了一段欢乐时光，直到冬天，根亮去城里购买食物和酒。在回程途中，他遇到了一些奇怪的事情。回到矿区后，他和郭老头共同度过了接下来的日子。根亮离开后，来到清水县城寻找齐老头，希望能一起做生意，但未找到。他在那里遇到了唱灯影的黄武英和他的女友樱桃。根亮回到家乡，与哥哥根明团聚。他们谈论根亮的经历和他未带回来的钱。根明和根亮决定为根亮和女朋友安排见面。同时，他们得知怀文家发生变故，妻子秋桃回了娘家。根亮决定帮忙寄信并寻找失踪多年的父亲李世荣。在崆峒山上，根亮四处打听，领悟到父亲其实在他心中。尽管面临困难，但在家人支持下，根亮决定来年再找。年底时节，三太爷因根亮回家愤怒，准备在除夕夜教训他。同时，根明发现永贵的女人还活着，她在外地唱牛皮灯影。根明和根亮为她上坟，震惊于她的死讯。这个故事展现了人性的复杂和矛盾，以及愤怒和悔恨之间的转变。"
}