{
    "chapter_title": "第六十七章  医院",
    "chapter_summary": "两位陌生人意外地在医院相遇。他们微笑着打招，表现出真诚的友谊。故事发生在一楼左侧的儿科诊室，这里远离交响乐般的婴儿哭声。主人公乘坐火箭抵达城市，降落在报刊亭附近。当他醒来时，发现周围是繁华的市区，而一辆受损严重的公交车在街道上艰难行驶，展现了这个城市的独特风貌。",
    "para_groups_num": 1,
    "para_groups": [
        {
            "id": 0,
            "content": "陌生人彼此微笑，像比邻的椅子一样真诚\n但开始的时候难免力不从心\n儿科室设在一楼左边，避免了上上下下\n交响团的哭声因此保持了低调\n去医院时我开着一架火箭，因为没有机场\n直接降落在了某报刊亭\n醒来后我身陷闹市，看见火热的街道上爬行着\n一辆伤势严重的公交车",
            "summary": "两个陌生人相遇并真诚地微笑。在医院里，儿科诊室设在一楼左侧，使得交响乐的哭声保持低调。主人公去医院时乘坐火箭直接降落在报刊亭附近。当他醒来时，发现自己身处繁华市区，看到一辆受损严重的公交车在街道上行驶。"
        }
    ]
}