{
    "novel_title": "车行途中",
    "tag": "['悬疑', '言情', '都市']",
    "source": [
        0,
        1,
        2
    ],
    "content": "第1部分：这部作品通过多种角色和场景，展现了现实生活中人们面临的挑战、变化和美好回忆。主人公在南方小镇的旅程中经历了时光的变化，并在回忆中寻找过去的美好。作者在河边遇到了一条充满忧伤的河流，回忆起某个人物悲剧性的经历。主人公试图找回失去的回忆，却在各种情感中挣扎。作品通过丰富的细节描绘了生活中的美好与变化，同时也深入探讨了人类之间的差异、联系和陌生感。\n第2部分：这部作品通过多种生活场景和人物描绘，展现了现实生活中的挑战、情感、哲学思考以及对生活的独特见解。从现实生活中的挑战到艺术、哲学的重要性，再到神秘事件和悬疑世界，作品涵盖了丰富的内容。同时，通过对不同人物的生活描绘，反映了作者对生活细节和心理的深入洞察。\n第3部分：这部作品通过丰富多样的情节和角色，展现了中国成都生活的艺术性、社会性和情感交织。故事围绕主人公的生活挑战、诗歌创作、对遥远地方的思念展开，涉及灵魂出窍、梦境回忆、日常生活价值等主题。作品还通过多个人物的故事线，探讨了艺术性问题、社会性问题以及不同人生观的碰撞。同时，作品以幽默和讽刺的方式讲述生活中的小确幸，赞美生活中琐事。在太阳之城，作者揭示了改善精神卫生的重要性，并对诗人揭示世界虚幻、罪恶和污秽的能力表示赞赏。春天的剧情展示了大自然的美好与活力，以及人们在春天里的活动。作者通过描述生活场景，表达对好友蒋浩的思念和关爱，关注现实生活中人们依赖网络维系情感联系的现象，并运用比喻、隐喻等手法表达对生活细节和现实思考的独特见解。这部选集汇集了作者近二十年来的96首诗歌，旨在影响自己和亲朋好友，并在未来留下美好的回忆。",
    "summary": "这部作品通过多样化的角色、场景和生活挑战，展现了现实生活中人们的情感、哲学思考和美好回忆。主人公在南方小镇的旅程中经历了时光的变迁，并在回忆中寻找过去的美好。作者在河边遇到一条忧伤的河流，回忆起某个悲剧性人物的遭遇。主人公试图找回失去的回忆，却在各种情感中挣扎。作品通过丰富的细节描绘了生活中的美好与变化，同时也深入探讨了人类之间的差异、联系和陌生感。此外，作品还涉及艺术、哲学重要性，神秘事件和悬疑世界等内容，反映作者对生活细节和心理的深入洞察。"
}