{
    "chapter_title": "第六十三章  涩涩的吻",
    "chapter_summary": "主人公与他的爱人伊燕共度时光，但由于主人公感冒，他们决定避免亲吻。尽管面临分离的阴影，伊燕依然表现出温柔体贴的一面。主人公躺在床上，对未来充满担忧，因为明天伊燕将成为别人的新娘。在鼓起勇气想要询问伊燕是否愿意一起私奔时，他们的对话被意外打断。",
    "para_groups_num": 1,
    "para_groups": [
        {
            "id": 0,
            "content": "我又连着打了几个喷嚏，身体也抖得越来越厉害了。看来，我确实是感冒了，这次的香吻又泡汤了。我想……这或许是我最后一次机会了。明天她将成为孪弋的新娘，我不再抱有幻想，因为毕竟我改变不了现实。或许更多时候，爱是脆弱的。\n伊燕看我的身体在发抖，低沉地说道：“你感冒了。算了，还是不要亲我了，免得又对着我打喷嚏。”\n说着，她站起身来，挪步到我的跟前看了看我，然后蹲下身帮我脱下了鞋，搀我在床上躺了下来，替我盖好了被子。没想到原本有着几分野蛮的她，此时此刻竟是如此柔情似水。\n我躺在被窝中仰望着她，万般幸福和甜美，然而一时的美好憧憬，很快便会被现实撞得支离破碎，甚至可以听到一声声响——只要她今晚离开我的房间，明天便将为孪弋穿上婚纱了。\n她站立在床前俯视着我，又莫名娇羞地一笑：“你感冒得这么严重，明天还能坐火车吗？”\n我看着她，挤出一丝笑：“没事的，或许明天就好了。反正火车票买好了，不走也得走，要不……谁报销这车票呀？”\n“那……”她低声说道，似若恋恋不舍，“我……我走了啊。”\n“嗯。”我心痛地凝视着她，微微点了点头。\n最终，她还是缓慢地转过了身，低下了头。\n此刻我更是心如刀割，因为她即将迈出的每一步，都在拉开我们的距离。我想……也许这是我最后一次见她了。\n如果……如果她愿意，我想诚诚恳恳地问她一次：愿意和我私奔吗？我爱你！好爱好爱你！\n可一想到她明天要为孪弋披上婚纱，我就难以开口，毕竟他们的婚礼也不是儿戏。\n或许从与她相识那天起，就注定了这最后的悲剧，因为那时她已经是孪弋的未婚妻了。然而她知道悲剧的存在，为何又和我……也许我的很多想法是错误的，也许她愿意同我私奔。\n爱，就要说出口。然而，我既然爱，为何又不抓住这最后的机会呢？想着这些，我凝望着她的背影，咬了咬牙，终于鼓足了勇气！不料，我刚要张嘴，她猛一转身，竟莫名地怒视着我。\n我瞅着她双眼冒着一种莫名的怒火，有些胆怯了。于是，我下意识地拽了拽被子，捂住胸口。因为我太了解她了，这种情况下，她一般都会大打出手，甚至不分轻重。\n我颤巍巍地注视着她，低声问道：“你……你不是说你舍不得打我了吗？”\n我的话刚落音，她已跨步上前，猛的一下，狠狠的一拳，捶打在我的胸口。\n“啊——”痛得我紧咬牙。\n瞅着我疼痛的样子，她伤心地落下了泪来，又狠狠一拳捶打在我的胸口，同时嚷道：“浑蛋！猪头！一头死猪！你就不能男人一回吗？你就不能挽留我吗？看见你这唯唯诺诺的样子，我就忍不住想揍你！”\n待她发泄完后，我满怀顾虑地看着她，低声道：“可是……”\n“可是什么？什么可是？”她瞪着我。\n“可是……你……明天……我想……”\n“到底可是什么？你想什么，你不说出来，我怎么知道。从头到尾你都没有真切地看着我的眼睛，对我说你爱我。”\n“我……”我低着头想了想，“我……我爱你，好爱好爱你！”\n听完我的话，她暗自一怔，一阵欣喜。“可是……”我忽然又说。\n“不要说可是。”她立即抢断了我的话，“我不想听了，我不想听‘可是’了。”她俯视着我，然后挪了挪步子，渐渐俯身欲吻我，并且慢慢闭上了双眼。\n我也涩涩地闭上了双眼。此刻，我感觉到了她的唇很薄、很柔，香香的、甜甜的……\n可谁料，这时居然传来了“咚咚”的拍门声。我反感地睁开双眼，她也睁开了双眼。\n“谁？”伊燕问道。\n“我，傻强。”\n“等等。”她说完后俯视着我，又猛的一下吻了吻我的双唇，那一瞬间的感觉很美！\n“伊小姐，你妈也来了。”\n门外的傻强又嚷了一声。\n“不是告诉你，在没有开门的时候，不能说我来了吗？”\n这时传来的是伊燕妈妈的声音。\n“可是小姐问谁，我哪敢忽略您！”\n“你……唉！”",
            "summary": "主人公与他的爱人伊燕在一起。由于感冒，他们决定不亲吻彼此，但伊燕却表现得非常温柔体贴。主人公躺在床上，心里充满了对未来的担忧，因为他知道明天伊燕将成为别人的新娘。他鼓起勇气想要询问伊燕是否愿意和他私奔，但在关键时刻，他们的对话被打断。"
        }
    ]
}