{
    "chapter_title": "第四十一章 ：蜗婚（56）",
    "chapter_summary": "主人公感到孤独无助，无法找到可以依靠的人。尽管她努力安慰自己，但现实的问题仍然困扰着她。就在此时，她接到了母亲的电话，这让她感受到了亲情的关爱和温暖。在意识到父母为她付出的无私之爱后，她决定隐瞒自己的困境，以便让母亲放心。",
    "para_groups_num": 1,
    "para_groups": [
        {
            "id": 0,
            "content": "我把手机里的通讯录翻了个遍，也没翻出一个可以打的电话，还有谁能会在三更半夜来管我呢？那些朋友都结婚了，有老公有孩子的，都是老公孩子热炕头的怎么好意思半夜去人家家里。\n人在这个最最无助的时候，想到的人，真正又有几个？\n我有些后悔刚才那么脑子一热就出来，明早还得早点回去给温安年的爸妈做饭，今晚的归宿还没有着落，小区里的灯大都灭了，这正是人人进入梦香的时刻，我却像是无主的幽魂一般凄凄艾艾。\n可是，真正能潇洒的起来吗？\n手机一闪一闪地，竟有人在这个时候给她打电话，一看，是妈，果真是我的亲娘啊，在女儿举目无亲的时候，我妈竟想起了我。\n“素素，你睡了没？”妈妈亲切的声音响在耳旁。\n我忙擦眼泪，假装打了个哈欠，说：“妈，我在睡觉呢，怎么了，怎么这么晚打电话给我，家里没什么事吧。www.kankankan8.cn”\n“没事，家里都好着呢。我刚才梦见你在一个黑暗的地方喊妈，一声声地喊的我揪心，一下把我喊醒了，醒来我就想打个电话给你，我才放心。”妈妈说。\n“你弟弟正在找工作，我也在给一家工厂的食堂做饭，我就是放心不下你啊，你不在妈身边，妈见不着你心就是不踏实。”我妈说。\n“妈，我挺好的啊，过段时间我就回来看你，我又长胖了呢，单位里又涨工资了，够我花的了。”我胡编着说。\n“素素，你别总在妈面前报喜不报忧啊，你和安年都还好吧？你告诉他，我养了几只大芦花鸡，下了不少蛋，下次你们回来你们把捎到南京去吃。”我妈高兴的说。\n“好呢，我到时和安年一起回来。”\n我用轻快的语音说着。\n挂了妈妈的电话，生出了感慨，那首歌唱的多正确，世上只有妈妈好，爱情是娘的狗屁，没有人能比我们的父母更爱我们，更爱的无私。\n脑子里冒出这句话，世界上每一种感情都是以相聚相守为目的的，只有亲情，父母把孩子养大，最终是分开。\n妈妈，你可知道，你的女儿，现在受着怎样的苦，我多想告诉你我现在经历的一切痛苦，可是，我不能，我不能再让我辛苦的妈妈再为我平添担心。\n妈妈，我爱你，我爱你，我爱你……我对着手机，一遍遍地说。",
            "summary": "在这个深夜，主人公找不到可以求助的人，感到孤独和无助。她试图安慰自己，但现实问题依然困扰着她。这时，她接到了母亲的电话，让她感受到了亲人的关爱和温暖。她意识到父母的付出和无私的爱，决定隐瞒自己的困境，让母亲安心。"
        }
    ]
}