{
    "chapter_title": "第十八章 ",
    "chapter_summary": "僵尸公主被石奴追击。突然，一口巨棺从地洞中飞出，引发异变。这一幕让碧衣妇人和叶惊天等人震惊。叶惊天和风慕容面对面站立，墓室中的气氛紧张。石奴双眼中充满杀意，铁拳紧握。地面塌陷形成了一个黑漆漆的地洞，让人好奇其中隐藏的强大存在。",
    "para_groups_num": 2,
    "para_groups": [
        {
            "id": 0,
            "content": "那僵尸公主似乎被这石奴的威势所摄，竟是不由自主向后退去。一直退到那翻倒的巨棺之前，这才停了下来。\n那石奴一吼之后，随即迈动脚步，一步一步向那僵尸公主逼了过去。眼看再有数息功夫，这石奴逼到那僵尸公主身前，一拳击出，便可将这僵尸公主打的筋折骨断。\n碧衣妇人嘿嘿一笑，心道：“看来这女僵尸不过尔尔，我这石奴再有一拳便可让这女僵尸毕命于斯。”心念转处，碧衣妇人的眼睛随即向叶惊天一横，脸上满是得意之色。似乎在说：“你看，这石奴打这女僵尸还不是像打倒那些毒僵尸一般容易。”\n叶惊天没有说话。只是双目凝注前方，看着墓室之中那石奴一步一步向那僵尸公主逼了过去。不知为何，叶惊天心中竟是不愿看到这僵尸公主被那石奴打得筋折骨断。\n叶惊天张了张嘴，正要开口劝说碧衣妇人召回那石奴，四人就此离去，也放那僵尸公主一马，免得这僵尸公主九泉之下还得不到一具全尸。可就在叶惊天张口还未说出这一句话之际，墓室之中异变陡生。\n只见那僵尸公主身旁的那一口巨棺之下募地传来一阵重物撞击石壁的咚咚之声。随着那撞击之声越来越强，那一口巨棺就仿佛身处风浪之中的一艘小舟一般，左右摇摆晃动不停。\n那撞击之声越来越响，越来越强。\n巨棺之下的地面也随即裂开数道裂缝。裂缝越来越大，到得最后，数条裂缝竟而贯通，紧接着，巨棺下面传来轰的一声大响，巨棺下面的地面竟然整个塌陷下去，露出一个十余丈方圆的大洞。\n那巨棺一歪，便倒向那地洞之中。\n那僵尸公主早已躲向墓室一边。\n碧衣妇人和叶惊天，风慕容三人看到这一幕都是骇然不已。三人心中都是转着一个念头：“这巨棺下面怎么会出现这么一个大洞？地洞之中又是什么在不住撞击地面？这才使得整个地面塌陷？”\n那石奴面对着这墓室之中的巨变，却是面不改色，只有一双瞳孔慢慢缩了起来。\n地洞塌陷持续了数十息之后，这才慢慢停止。只不过才安静了不过片刻，那地洞之中募地飞起来一件物事。\n那物事不是别的，正是适才落入地洞之中的那一口巨棺。\n巨棺似乎被一股来自地洞之中的大力猛地顶起，飞了出来。直撞到墓室南侧石壁，发出怦然一声大震，这才落了下来。\n那巨棺如此之重，竟然被这地洞下面传来的这一股大力震得飞起。这一股力量该是何等霸道？",
            "summary": "僵尸公主被石奴追击，但突然墓室中出现异变，一口巨棺从地洞中飞出，撞在石壁上。原来地洞下方有一股强大的力量，使得巨棺被震飞出来。这个变故让碧衣妇人和叶惊天等人感到震惊。"
        },
        {
            "id": 1,
            "content": "叶惊天和风慕容面面相觑。\n碧衣妇人脸上动容。\n石奴的一双眼睛之中的凶煞之气募地一长。\n跟着石奴的一双铁拳慢慢攥紧。\n这墓室之中杀气四溢。\n这杀气不光是来自石奴的一双眼睛，更多的竟是来自那地面塌陷形成的那一个黑漆漆的地洞之中。\n这地洞下面究竟是什么物事，竟然散发出如此强大的杀气？",
            "summary": "叶惊天和风慕容面对面的站着。碧衣妇人被眼前的情景所震惊，而石奴的双眼中流露出强烈的杀意。随着石奴的铁拳逐渐握紧，墓室中的气氛变得紧张。这股杀气不仅来自于石奴的眼睛，更源自于地面塌陷后形成的黑漆漆地洞，令人好奇其中究竟隐藏着什么强大的存在。"
        }
    ]
}