{
    "chapter_title": "第一百一十二章  她什么都不需要做 宛如一道最耀眼夺目的风景 (11)",
    "chapter_summary": "韩睿独自坐在沙发上抽着烟，陷入沉思。这时，朋友方晨敲门进来，想找杯水喝。她注意到韩睿的不寻常表现，心生疑惑。方晨猜测韩睿的异常可能与他最近的生意或感情生活有关，但考虑到他们之间的关系，她觉得感情问题不太可能。然而，她决定还是问问韩睿发生了什么事，以便帮助他度过难关。",
    "para_groups_num": 1,
    "para_groups": [
        {
            "id": 0,
            "content": "韩睿仍旧深陷在沙发里一动不动，只是抬起眼睛看向她。\n“为什么不开灯？”她问。\n其实在这么黑的地方，照理说应该什么都看不清，可是她似乎可以清楚感受到他的目光，正越过小小的厅堂向她投射过来，深沉晦暗得犹如夜空下无边无尽的海。\n她解释道：“我来找水喝。”\n韩睿将剩下的香烟递到唇边猛吸了两口，然后捻熄在手边的烟灰缸里，站起身，转过去打开大门。\n猎猎的风一下子灌进来，带着山林间特有的湿润凉意，直接穿过身上单薄的衣料。\n方晨正好拿着矿泉水瓶走出来，毫无防备地被这样一吹，不禁瑟缩了一下肩膀，好奇道：“你要出去？”\n“没有。”韩睿应声回头的同时，顺手阖上了门板。\n她却不由得又多看了他两眼，到了嘴边的话欲言又止。\n太奇怪了。\n直觉告诉她，今天的他有些反常。\n她不知道他在想什么，也不知道发生了什么事情，才会令他如此在三更半夜，一个人坐在客厅里抽烟。\n是因为生意？抑或是因为感情？\n应该不可能是后者，她暗自猜想。\n因为就连他自己都说了，他从没爱过任何人。\n既然没有爱，那又何来的烦恼？",
            "summary": "韩睿在深夜坐在沙发上抽烟，而方晨来找水喝。韩睿显得有些反常，让方晨感到好奇。直觉告诉方晨，韩睿的异常可能与生意或感情有关，但她认为不可能是后者，因为韩睿从未爱过任何人。"
        }
    ]
}