{
    "chapter_title": "第十六章  三个先进",
    "chapter_summary": "带灯虽然没有实现她的第一个愿望，但她学会了接受生活中的无法改变之事。在工作中，她努力提升自己，逐渐取得了显著的进步。每当有奖励和评选机会出现时，其他同事都会争相竞争，而带灯则保持谦虚的态度，凭借她的努力和实力，连续三年获得了先进的荣誉。",
    "para_groups_num": 1,
    "para_groups": [
        {
            "id": 0,
            "content": "带灯没有实现第一件她想干的事，她得出的经验是：既然改变不了那不能接受的，乃就接受那不能改变的。\n她再没有过任何建议，镇政府分配她干什么，她就去干什么，尽力干好。\n奖励部分干部的一级工资了，大家都争着，像鸡掐仗。\n而每年要评一次先进，没有钱，可以有张奖状，能去县城开会，大家就客气了，说：让带灯当！带灯就有了三个先进。",
            "summary": "带灯没有实现她的第一个愿望，学会了接受无法改变的事情。在镇政府分配的工作中，她努力工作并取得了进步。当有奖励和评选机会时，大家争相争取，而带灯则表现得谦虚，获得了三次先进荣誉。"
        }
    ]
}