{
    "chapter_title": "第六十六章  鲛人鱼油",
    "chapter_summary": "水天波被困住了，他的食物只够吃三天。为了延长停留时间，他决定吃掉随身携带的小绵羊。与此同时，他还受了重伤，需要补充体力。因此，他宰杀小绵羊并准备烤食。幸运的是，他在棺材旁发现了一口装有鲛人鱼膏的铜盆，可以用来点燃烤肉。",
    "para_groups_num": 1,
    "para_groups": [
        {
            "id": 0,
            "content": "水天波思忱自己身边所带的干粮只够维持三天之需，看来要想在这墓室之中多耗几天，别无良策，只有将这小绵羊吃了。\n而他自己身上的伤势也是不轻，敷药之后，血流已经止住。但是体内却是甚为虚弱，饱餐一端之后，体力也许会增加许多，是以这水天波当即决定将小绵羊杀了。\n水天波乃是行事果断之人，既然已经决定，再不考虑。当即掏出那柄锋利之极的短刀，在一侧墓室墙壁之上，剜了一个窟窿。而后将那根火折子插在那窟窿之中。\n手提短刀，复又走到那只小绵羊跟前。一脚伸出，踩在小绵羊身上。左手握刀，手起刀落。只听嗤嗤嗤嗤几下声响。片刻之间已然将一只小绵羊剥去羊皮，而后开膛破肚，将小绵羊收拾干净，切做十来块。\n这其间，风冷清却是没有回过头来。\n水灵也是紧皱双眉。看着爷爷在一旁手脚利落的收拾着小绵羊。\n水天波收拾干净之后，眼光四下里望去，好寻找一些木头之类的物事，以便能够点燃，好将这羊肉烤熟。倘然找不到一些引燃之物，那也只能茹毛饮血，生吃这羊肉了。\n所幸的是，水天波眼光一转，便即在这间墓室那一口黑漆棺木之前发现一个黄澄澄的物事。\n水天波心中一动，当即走了过去。走到那黄澄澄的物事跟前，这才发现那物事原来是一口铜盆。\n铜盆之中装着半盆黑黝黝的物事。\n水天波伸手一碰，那黄铜盆微微一晃，铜盆内的物事竟然左右晃动起来。\n看来那黄铜盆内的物事是一种类似于油膏之类的物事。\n水天波低头一闻，一股刺鼻的鱼腥味扑鼻而来。\n水天波心中一动，心道：“这铜盆里的物事莫非是鲛人的鱼膏所制成的？”",
            "summary": "水天波在墓室中被困，他的干粮只能维持三天。为了延长停留时间，他决定吃掉随身的小绵羊。同时，他受伤严重，需要增加体力。于是他将小绵羊宰杀，准备烧烤。幸运的是，他在棺材前找到了一口装有鲛人鱼膏的铜盆，可以用来引燃烤肉。"
        }
    ]
}