{
    "chapter_title": "第九十一章  密洞",
    "chapter_summary": "水天波带着风冷清和水灵穿越幽暗小径，抵达一个隐藏在荆棘丛后的神秘洞穴。水灵充满好奇地进入洞穴，而在她的邀请下，风冷清也紧随其后。水天波随后进入洞穴并重新掩盖了洞口。",
    "para_groups_num": 1,
    "para_groups": [
        {
            "id": 0,
            "content": "水天波对二人道：“跟我来。”随即当先带路。慢慢穿过竹林走了进去。\n这湘妃竹林甚是茂密。水天波带着二人慢慢走了进去。\n越往里走，这竹林里面越是幽暗。阳光透过竹林的缝隙照了进来，只投下一片稀疏的光影。\n风冷清和水灵两个孩子身量甚小，行走在这竹林之中，倒不觉的如何挤迫。\n也不知过了多长时间。风冷清只觉得水天波曲曲折折，或东或西，拐来拐去，终于在一处茂密的荆棘丛前停了下来。\n水灵疑惑道：“爷爷，到了吗？”\n水天波点点头。\n风冷清和水灵站在这荆棘丛前发呆。\n两个人你看看我，我看看你，心道：“到这里干什么？”\n水天波见两个小孩都是非常疑惑，微微一笑。走到荆棘丛左侧，伸手轻轻掀起一侧的秘密的荆棘。\n荆棘后面赫然出现一个洞口。\n那洞口只有两丈方圆大小。洞里面黑漆漆的一片，也不知道究竟有多深。\n水灵一声欢呼，当即钻了进去。\n这水灵跟随爷爷日久，日夕熏陶，耳濡目染。对于这深山老林之中的密洞幽谷自是大感兴趣。且有爷爷在后压阵，自也是不怕有何危险。\n水灵钻进洞口，跑出数丈开外，见风冷清还在后面，迟疑未动。随即转身跑了出来，一把拉住风冷情的手臂，道：“风哥哥，走啊，咱们去洞里看看，有什么好玩的物事没有。”\n风冷清被水灵拉着，身不由主的跟了进去。\n水天波这一次跟在二人后面，也钻进洞口。\n而后将那覆盖洞口的荆棘放下。\n跟在水灵和风冷清的后面，走了进去。\n这山洞里面黑漆漆的一片。\n深不见底。\n水灵和风冷清只觉心里有些兴奋，又有些小小的害怕。\n水天波沉声道：“灵儿，风儿，慢点走。\n把火折子拿上。”\n说着一抖手，一根火折子迎风而亮，随即向水灵掷了过去。",
            "summary": "水天波带领风冷清和水灵进入一片茂密的湘妃竹林，穿过幽暗的小径，来到一个隐藏在荆棘丛后的洞穴。水灵兴奋地钻入洞穴，而风冷清则在水灵的邀请下跟着进去。水天波随后进入洞穴，并将洞口重新遮盖。"
        }
    ]
}